{
  "totalStudents": 172,
  "totalTeachers": 12,
  "totalSubjects": 8,
  "totalEvents": 6,
  "startDate": "19/11/2024",
  "endDate": "24/11/2024",
  "details": {
    "students": [
      {
        "id": 20489,
        "name": "คุณโก๋(ร้องเพลง)",
        "classes": [
          "ร้องเพลง (ห้องอัด)"
        ]
      },
      {
        "id": 20492,
        "name": "เก้าsw",
        "classes": [
          "ว่ายน้ำ"
        ]
      },
      {
        "id": 20214,
        "name": "ปันปอน",
        "classes": [
          "ว่ายน้ำ",
          "เปียโน"
        ]
      },
      {
        "id": 20317,
        "name": "โลมา sw",
        "classes": [
          "ว่ายน้ำ"
        ]
      },
      {
        "id": 20104,
        "name": "แพรวา",
        "classes": [
          "ว่ายน้ำ"
        ]
      },
      {
        "id": 20109,
        "name": "ไอคิว",
        "classes": [
          "เปียโน"
        ]
      },
      {
        "id": 20158,
        "name": "นโม ป.2",
        "classes": [
          "เปียโน"
        ]
      },
      {
        "id": 20484,
        "name": "ปั้นจั่น(พี่)sw",
        "classes": [
          "ว่ายน้ำ",
          "ตีกลอง"
        ]
      },
      {
        "id": 20079,
        "name": "มาร์ติน",
        "classes": [
          "ว่ายน้ำ"
        ]
      },
      {
        "id": 20284,
        "name": "ฮอมฮัก",
        "classes": [
          "เปียโน",
          "ว่ายน้ำ"
        ]
      },
      {
        "id": 20494,
        "name": "แบม แบม",
        "classes": [
          "ติวเตอร์"
        ]
      },
      {
        "id": 20493,
        "name": "อิ่มเอม",
        "classes": [
          "ติวเตอร์"
        ]
      },
      {
        "id": 20514,
        "name": "โซ(ร้องเพลง)",
        "classes": [
          "ร้องเพลง (ห้องอัด)"
        ]
      },
      {
        "id": 20196,
        "name": "สตาร์ท",
        "classes": [
          "ตีกลอง"
        ]
      },
      {
        "id": 20262,
        "name": "ฟอร์จูน",
        "classes": [
          "ว่ายน้ำ"
        ]
      },
      {
        "id": 20081,
        "name": "พาสต้า",
        "classes": [
          "ว่ายน้ำ"
        ]
      },
      {
        "id": 20459,
        "name": "แผ่นดินsw",
        "classes": [
          "ว่ายน้ำ"
        ]
      },
      {
        "id": 20378,
        "name": "โกฮัง",
        "classes": [
          "ว่ายน้ำ"
        ]
      },
      {
        "id": 20192,
        "name": "ยูโร",
        "classes": [
          "ตีกลอง"
        ]
      },
      {
        "id": 20490,
        "name": "ใบเฟิร์น(ร้องเพลง)",
        "classes": [
          "ร้องเพลง (ห้องอัด)"
        ]
      },
      {
        "id": 20482,
        "name": "เจ๋งเป้งsw",
        "classes": [
          "ว่ายน้ำ"
        ]
      },
      {
        "id": 20429,
        "name": "นารา",
        "classes": [
          "ว่ายน้ำ"
        ]
      },
      {
        "id": 20506,
        "name": "พอร์ช sw",
        "classes": [
          "ว่ายน้ำ",
          "ตีกลอง"
        ]
      },
      {
        "id": 20088,
        "name": "ฟีฟ่า",
        "classes": [
          "ตีกลอง",
          "เปียโน"
        ]
      },
      {
        "id": 20153,
        "name": "ฟามมี่",
        "classes": [
          "ตีกลอง"
        ]
      },
      {
        "id": 20387,
        "name": "ปุณย์",
        "classes": [
          "ว่ายน้ำ"
        ]
      },
      {
        "id": 20350,
        "name": "อันดามัน",
        "classes": [
          "ว่ายน้ำ",
          "เปียโน"
        ]
      },
      {
        "id": 20131,
        "name": "ณณิณ",
        "classes": [
          "ว่ายน้ำ"
        ]
      },
      {
        "id": 20193,
        "name": "ลิสา",
        "classes": [
          "ตีกลอง"
        ]
      },
      {
        "id": 20189,
        "name": "เบญญ่า",
        "classes": [
          "ตีกลอง"
        ]
      },
      {
        "id": 20477,
        "name": "ม่อน(ร้องเพลง)",
        "classes": [
          "ร้องเพลง (ห้องอัด)"
        ]
      },
      {
        "id": 20438,
        "name": "โปรดปราน",
        "classes": [
          "เปียโน"
        ]
      },
      {
        "id": 20369,
        "name": "เรย์",
        "classes": [
          "ว่ายน้ำ"
        ]
      },
      {
        "id": 20430,
        "name": "อ้อม",
        "classes": [
          "กีต้าร์"
        ]
      },
      {
        "id": 20271,
        "name": "ฮาเปอร์",
        "classes": [
          "ตีกลอง"
        ]
      },
      {
        "id": 20222,
        "name": "พอตเตอร์(บ้านเด็กดี) อาญ่า",
        "classes": [
          "ตีกลอง"
        ]
      },
      {
        "id": 20183,
        "name": "ภูริ",
        "classes": [
          "ตีกลอง"
        ]
      },
      {
        "id": 20140,
        "name": "ชินจัง",
        "classes": [
          "ตีกลอง"
        ]
      },
      {
        "id": 20467,
        "name": "อินวา",
        "classes": [
          "ว่ายน้ำ"
        ]
      },
      {
        "id": 20115,
        "name": "สกาย (บ้านเด็กดี)",
        "classes": [
          "ว่ายน้ำ"
        ]
      },
      {
        "id": 20469,
        "name": "ขุนเขาsw",
        "classes": [
          "ว่ายน้ำ"
        ]
      },
      {
        "id": 20385,
        "name": "กวินท์ (ลินดา)",
        "classes": [
          "ว่ายน้ำ"
        ]
      },
      {
        "id": 20256,
        "name": "อาร์ญ่า",
        "classes": [
          "ว่ายน้ำ"
        ]
      },
      {
        "id": 20465,
        "name": "น้องไอติม",
        "classes": [
          "เปียโน"
        ]
      },
      {
        "id": 20434,
        "name": "ไออุ่น",
        "classes": [
          "เปียโน"
        ]
      },
      {
        "id": 20337,
        "name": "ธามเมอร์",
        "classes": [
          "ว่ายน้ำ"
        ]
      },
      {
        "id": 20342,
        "name": "ติวเตอร์ (SW)",
        "classes": [
          "ว่ายน้ำ",
          "ติวเตอร์"
        ]
      },
      {
        "id": 20152,
        "name": "ดีดี",
        "classes": [
          "เปียโน"
        ]
      },
      {
        "id": 20180,
        "name": "ไอริณ",
        "classes": [
          "เปียโน"
        ]
      },
      {
        "id": 20391,
        "name": "ดินแดน",
        "classes": [
          "ว่ายน้ำ"
        ]
      },
      {
        "id": 20392,
        "name": "ฟ้าใหม่",
        "classes": [
          "ว่ายน้ำ"
        ]
      },
      {
        "id": 20371,
        "name": "กวิน(ดอยหล่อ)",
        "classes": [
          "ว่ายน้ำ"
        ]
      },
      {
        "id": 20341,
        "name": "ไตเติ้ล (SW)",
        "classes": [
          "ว่ายน้ำ",
          "ติวเตอร์"
        ]
      },
      {
        "id": 20154,
        "name": "ตังตัง",
        "classes": [
          "เปียโน"
        ]
      },
      {
        "id": 20498,
        "name": "ฟิลเตอร์(เต้น)",
        "classes": [
          "เต้น"
        ]
      },
      {
        "id": 20502,
        "name": "เฟรน(เต้น)",
        "classes": [
          "เต้น"
        ]
      },
      {
        "id": 20503,
        "name": "โฟร์(เต้น)",
        "classes": [
          "เต้น"
        ]
      },
      {
        "id": 20505,
        "name": "เกียร์(เต้น)",
        "classes": [
          "เต้น"
        ]
      },
      {
        "id": 20504,
        "name": "มิ้น(เต้น)",
        "classes": [
          "เต้น"
        ]
      },
      {
        "id": 20500,
        "name": "โอพี(เต้น)",
        "classes": [
          "เต้น"
        ]
      },
      {
        "id": 20499,
        "name": "พีช(เต้น)",
        "classes": [
          "เต้น"
        ]
      },
      {
        "id": 20501,
        "name": "น้ำเมย(เต้น)",
        "classes": [
          "เต้น"
        ]
      },
      {
        "id": 20306,
        "name": "โอบกอด",
        "classes": [
          "ว่ายน้ำ"
        ]
      },
      {
        "id": 20169,
        "name": "ฟิวเจอร์",
        "classes": [
          "เปียโน",
          "ร้องเพลง (ห้องอัด)"
        ]
      },
      {
        "id": 20267,
        "name": "เจเจ",
        "classes": [
          "ว่ายน้ำ"
        ]
      },
      {
        "id": 20419,
        "name": "น้ำเหนือ",
        "classes": [
          "ว่ายน้ำ"
        ]
      },
      {
        "id": 20420,
        "name": "น้ำใส",
        "classes": [
          "ว่ายน้ำ"
        ]
      },
      {
        "id": 20428,
        "name": "จัสมิน",
        "classes": [
          "ว่ายน้ำ"
        ]
      },
      {
        "id": 20401,
        "name": "มน",
        "classes": [
          "ตีกลอง"
        ]
      },
      {
        "id": 20172,
        "name": "มิลิณ",
        "classes": [
          "เปียโน"
        ]
      },
      {
        "id": 20119,
        "name": "อิ่มอุ่น",
        "classes": [
          "เปียโน"
        ]
      },
      {
        "id": 20179,
        "name": "ไอติม",
        "classes": [
          "เปียโน"
        ]
      },
      {
        "id": 20389,
        "name": "พอดี",
        "classes": [
          "เปียโน"
        ]
      },
      {
        "id": 20396,
        "name": "ด้วงเดช",
        "classes": [
          "ตีกลอง"
        ]
      },
      {
        "id": 20423,
        "name": "ต้นน้ำ",
        "classes": [
          "ตีกลอง"
        ]
      },
      {
        "id": 20217,
        "name": "แฝด อิ่ม",
        "classes": [
          "เครื่องสาย"
        ]
      },
      {
        "id": 20218,
        "name": "แฝด เอ็ม",
        "classes": [
          "เครื่องสาย"
        ]
      },
      {
        "id": 20219,
        "name": "แฝด อุ่น",
        "classes": [
          "เครื่องสาย"
        ]
      },
      {
        "id": 20365,
        "name": "วุ้นเส้น",
        "classes": [
          "เครื่องสาย"
        ]
      },
      {
        "id": 20261,
        "name": "พี่ข้าวหอม",
        "classes": [
          "เครื่องสาย"
        ]
      },
      {
        "id": 20130,
        "name": "ลลิล",
        "classes": [
          "เปียโน",
          "ร้องเพลง (ห้องอัด)"
        ]
      },
      {
        "id": 20297,
        "name": "เอแคร์",
        "classes": [
          "เปียโน"
        ]
      },
      {
        "id": 20426,
        "name": "ญาญ่า(กีต้าร์)",
        "classes": [
          "กีต้าร์"
        ]
      },
      {
        "id": 20186,
        "name": "เนล",
        "classes": [
          "เปียโน",
          "ตีกลอง"
        ]
      },
      {
        "id": 20289,
        "name": "จีวา",
        "classes": [
          "ว่ายน้ำ"
        ]
      },
      {
        "id": 20076,
        "name": "วินวิน",
        "classes": [
          "เปียโน"
        ]
      },
      {
        "id": 20161,
        "name": "เนย",
        "classes": [
          "เปียโน"
        ]
      },
      {
        "id": 20292,
        "name": "ลินดา sw",
        "classes": [
          "เปียโน"
        ]
      },
      {
        "id": 20299,
        "name": "เพชรจ้า",
        "classes": [
          "ว่ายน้ำ"
        ]
      },
      {
        "id": 20291,
        "name": "ซันญ่า",
        "classes": [
          "ว่ายน้ำ"
        ]
      },
      {
        "id": 20384,
        "name": "มานา",
        "classes": [
          "ว่ายน้ำ",
          "เปียโน"
        ]
      },
      {
        "id": 20486,
        "name": "เอด้า(เปียโน)",
        "classes": [
          "เปียโน"
        ]
      },
      {
        "id": 20460,
        "name": "ชิริว",
        "classes": [
          "ว่ายน้ำ"
        ]
      },
      {
        "id": 20444,
        "name": "วาวา",
        "classes": [
          "ว่ายน้ำ"
        ]
      },
      {
        "id": 20406,
        "name": "พีต้า",
        "classes": [
          "ว่ายน้ำ"
        ]
      },
      {
        "id": 20156,
        "name": "ทิกเกอร์",
        "classes": [
          "เปียโน"
        ]
      },
      {
        "id": 20178,
        "name": "อุ๊งอิ๊ง",
        "classes": [
          "ตีกลอง"
        ]
      },
      {
        "id": 20363,
        "name": "พอใจ(เปียโน)",
        "classes": [
          "เปียโน"
        ]
      },
      {
        "id": 20212,
        "name": "เอื้อ",
        "classes": [
          "ตีกลอง"
        ]
      },
      {
        "id": 20173,
        "name": "ริบบิ้น",
        "classes": [
          "เปียโน"
        ]
      },
      {
        "id": 20160,
        "name": "นะโม ป.3",
        "classes": [
          "เปียโน"
        ]
      },
      {
        "id": 20157,
        "name": "เจตต์",
        "classes": [
          "ตีกลอง",
          "กีต้าร์"
        ]
      },
      {
        "id": 20395,
        "name": "อัฒฑ์",
        "classes": [
          "ตีกลอง"
        ]
      },
      {
        "id": 20101,
        "name": "โอโซน",
        "classes": [
          "ตีกลอง"
        ]
      },
      {
        "id": 20147,
        "name": "จอห์น",
        "classes": [
          "กีต้าร์",
          "เปียโน"
        ]
      },
      {
        "id": 20220,
        "name": "ไพลิน",
        "classes": [
          "เปียโน"
        ]
      },
      {
        "id": 20293,
        "name": "พอตเตอร์",
        "classes": [
          "ว่ายน้ำ"
        ]
      },
      {
        "id": 20410,
        "name": "ปริมsw",
        "classes": [
          "เปียโน",
          "ว่ายน้ำ"
        ]
      },
      {
        "id": 20344,
        "name": "เปรม",
        "classes": [
          "เปียโน"
        ]
      },
      {
        "id": 20175,
        "name": "อองตอง",
        "classes": [
          "เปียโน"
        ]
      },
      {
        "id": 20487,
        "name": "ติวเตอร์ (เล็ก)",
        "classes": [
          "ว่ายน้ำ"
        ]
      },
      {
        "id": 20247,
        "name": "วาเลนไท",
        "classes": [
          "ตีกลอง"
        ]
      },
      {
        "id": 20213,
        "name": "เนตั้น",
        "classes": [
          "ตีกลอง"
        ]
      },
      {
        "id": 20144,
        "name": "คุณโร่",
        "classes": [
          "เปียโน"
        ]
      },
      {
        "id": 20290,
        "name": "ภูรี",
        "classes": [
          "ว่ายน้ำ"
        ]
      },
      {
        "id": 20373,
        "name": "โอชิน",
        "classes": [
          "ว่ายน้ำ"
        ]
      },
      {
        "id": 20393,
        "name": "ปุณณ์ปุณณ์",
        "classes": [
          "ว่ายน้ำ"
        ]
      },
      {
        "id": 20418,
        "name": "ปลื้ม(พี่)",
        "classes": [
          "ว่ายน้ำ"
        ]
      },
      {
        "id": 20417,
        "name": "ปริม(น้อง)",
        "classes": [
          "ว่ายน้ำ"
        ]
      },
      {
        "id": 20075,
        "name": "วาชิ",
        "classes": [
          "ว่ายน้ำ"
        ]
      },
      {
        "id": 20448,
        "name": "โอดิน",
        "classes": [
          "ว่ายน้ำ"
        ]
      },
      {
        "id": 20409,
        "name": "เจ้านาง",
        "classes": [
          "เปียโน"
        ]
      },
      {
        "id": 20326,
        "name": "มิรา",
        "classes": [
          "เปียโน"
        ]
      },
      {
        "id": 20455,
        "name": "กตังค์",
        "classes": [
          "ตีกลอง"
        ]
      },
      {
        "id": 20086,
        "name": "โมเดล",
        "classes": [
          "เปียโน"
        ]
      },
      {
        "id": 20413,
        "name": "น้ำอบ",
        "classes": [
          "ตีกลอง"
        ]
      },
      {
        "id": 20111,
        "name": "จูเนียร์",
        "classes": [
          "ตีกลอง",
          "ว่ายน้ำ"
        ]
      },
      {
        "id": 20512,
        "name": "เมซซี่",
        "classes": [
          "ติวเตอร์"
        ]
      },
      {
        "id": 20199,
        "name": "ซีโน่",
        "classes": [
          "ตีกลอง"
        ]
      },
      {
        "id": 20210,
        "name": "คอสมิค",
        "classes": [
          "ตีกลอง"
        ]
      },
      {
        "id": 20145,
        "name": "เครปเค้ก",
        "classes": [
          "เปียโน"
        ]
      },
      {
        "id": 20134,
        "name": "โมเดล K.3",
        "classes": [
          "เปียโน"
        ]
      },
      {
        "id": 20340,
        "name": "ซีน่า (SW)",
        "classes": [
          "ว่ายน้ำ"
        ]
      },
      {
        "id": 20318,
        "name": "มีคุณ",
        "classes": [
          "ว่ายน้ำ"
        ]
      },
      {
        "id": 20237,
        "name": "ฟีฟ่า (ฟามมี)",
        "classes": [
          "ตีกลอง"
        ]
      },
      {
        "id": 20162,
        "name": "บูเก้ต์",
        "classes": [
          "เปียโน"
        ]
      },
      {
        "id": 20481,
        "name": "มินดา(โต)",
        "classes": [
          "เปียโน"
        ]
      },
      {
        "id": 20397,
        "name": "เจดรีม",
        "classes": [
          "เปียโน"
        ]
      },
      {
        "id": 20310,
        "name": "โมนา(น้อง)",
        "classes": [
          "เปียโน",
          "ว่ายน้ำ"
        ]
      },
      {
        "id": 20311,
        "name": "โตโน่ (พี่)",
        "classes": [
          "เปียโน"
        ]
      },
      {
        "id": 20475,
        "name": "แฮปปี้ (กีต้าร์)",
        "classes": [
          "กีต้าร์"
        ]
      },
      {
        "id": 20474,
        "name": "สวนไผ่(Piano)",
        "classes": [
          "เปียโน"
        ]
      },
      {
        "id": 20480,
        "name": "ขวัญข้าว(พี่) SW",
        "classes": [
          "ว่ายน้ำ"
        ]
      },
      {
        "id": 20479,
        "name": "ขุนเขา(น้อง)SW",
        "classes": [
          "ว่ายน้ำ"
        ]
      },
      {
        "id": 20244,
        "name": "จิน(SW)",
        "classes": [
          "ว่ายน้ำ"
        ]
      },
      {
        "id": 20308,
        "name": "อาโป",
        "classes": [
          "ว่ายน้ำ"
        ]
      },
      {
        "id": 20485,
        "name": "ชัดเจนSW",
        "classes": [
          "ว่ายน้ำ"
        ]
      },
      {
        "id": 20164,
        "name": "ปันนา",
        "classes": [
          "เปียโน"
        ]
      },
      {
        "id": 20187,
        "name": "นาวา",
        "classes": [
          "ตีกลอง"
        ]
      },
      {
        "id": 20403,
        "name": "ธันวา",
        "classes": [
          "กีต้าร์"
        ]
      },
      {
        "id": 20139,
        "name": "คิน",
        "classes": [
          "ตีกลอง"
        ]
      },
      {
        "id": 20431,
        "name": "ออน",
        "classes": [
          "เปียโน"
        ]
      },
      {
        "id": 20461,
        "name": "นาเนียร์(โต)",
        "classes": [
          "เปียโน"
        ]
      },
      {
        "id": 20177,
        "name": "อันดา",
        "classes": [
          "เปียโน"
        ]
      },
      {
        "id": 20168,
        "name": "ฟ้าใส",
        "classes": [
          "เปียโน"
        ]
      },
      {
        "id": 20266,
        "name": "ณดล",
        "classes": [
          "ตีกลอง"
        ]
      },
      {
        "id": 20098,
        "name": "กันหยง",
        "classes": [
          "ตีกลอง"
        ]
      },
      {
        "id": 20204,
        "name": "ต้นกล้า",
        "classes": [
          "กีต้าร์"
        ]
      },
      {
        "id": 20296,
        "name": "ไอด้า",
        "classes": [
          "เปียโน"
        ]
      },
      {
        "id": 20334,
        "name": "ลีโอ",
        "classes": [
          "ว่ายน้ำ"
        ]
      },
      {
        "id": 20201,
        "name": "ภัทร",
        "classes": [
          "ตีกลอง"
        ]
      },
      {
        "id": 20141,
        "name": "คมิก",
        "classes": [
          "เปียโน"
        ]
      },
      {
        "id": 20181,
        "name": "เฮ้าส์",
        "classes": [
          "เปียโน"
        ]
      },
      {
        "id": 20170,
        "name": "ภูพิงค์",
        "classes": [
          "เปียโน"
        ]
      },
      {
        "id": 20176,
        "name": "อะคิระ",
        "classes": [
          "เปียโน"
        ]
      },
      {
        "id": 20255,
        "name": "เติมเต็ม",
        "classes": [
          "ว่ายน้ำ"
        ]
      },
      {
        "id": 20250,
        "name": "มีตัง",
        "classes": [
          "ว่ายน้ำ"
        ]
      },
      {
        "id": 20132,
        "name": "แบ่งปัน",
        "classes": [
          "ว่ายน้ำ"
        ]
      },
      {
        "id": 20339,
        "name": "ปรานชีวา (SW)แบ่งปัน",
        "classes": [
          "ว่ายน้ำ"
        ]
      },
      {
        "id": 20329,
        "name": "ไอแคน",
        "classes": [
          "กีต้าร์"
        ]
      },
      {
        "id": 20191,
        "name": "มังกร",
        "classes": [
          "ตีกลอง",
          "กีต้าร์"
        ]
      },
      {
        "id": 20194,
        "name": "ข้าวหอม (กีต้าร์-รำไทย)",
        "classes": [
          "กีต้าร์"
        ]
      }
    ],
    "teachers": [
      {
        "id": 1,
        "name": "ครูฟอร์ด",
        "subjects": [
          "ร้องเพลง (ห้องอัด)",
          "เปียโน"
        ],
        "students": [
          20489,
          20109,
          20158,
          20284,
          20514,
          20490,
          20477,
          20438,
          20465,
          20434,
          20152,
          20180,
          20154,
          20169,
          20172,
          20119,
          20214,
          20179,
          20389,
          20297,
          20186,
          20130,
          20076,
          20161,
          20292,
          20486,
          20156,
          20363,
          20173,
          20160,
          20220,
          20410,
          20344,
          20175,
          20147,
          20144,
          20409,
          20326,
          20384,
          20350,
          20086,
          20145,
          20134,
          20162,
          20481,
          20397,
          20310,
          20311,
          20474,
          20164,
          20431,
          20461,
          20177,
          20168,
          20296,
          20141,
          20181,
          20170,
          20176,
          20088
        ]
      },
      {
        "id": 20,
        "name": "ครูเบนซ์",
        "subjects": [
          "ว่ายน้ำ"
        ],
        "students": [
          20492,
          20262,
          20467,
          20391,
          20420,
          20369,
          20385,
          20306,
          20289,
          20299,
          20291,
          20384,
          20406,
          20484,
          20410,
          20448,
          20340,
          20479,
          20485,
          20318,
          20387
        ]
      },
      {
        "id": 31,
        "name": "ครูขนุน",
        "subjects": [
          "ว่ายน้ำ"
        ],
        "students": [
          20214,
          20317,
          20081,
          20482,
          20350,
          20115,
          20256,
          20337,
          20342,
          20341,
          20267,
          20111
        ]
      },
      {
        "id": 8,
        "name": "ครูเนย",
        "subjects": [
          "ว่ายน้ำ"
        ],
        "students": [
          20104,
          20079,
          20378,
          20387,
          20131,
          20392,
          20371,
          20428,
          20256,
          20262,
          20460,
          20487,
          20290,
          20373,
          20418,
          20417,
          20391,
          20384,
          20480,
          20244,
          20308,
          20310,
          20255,
          20339
        ]
      },
      {
        "id": 30,
        "name": "ครูฮาท",
        "subjects": [
          "ว่ายน้ำ"
        ],
        "students": [
          20484,
          20459,
          20506,
          20469,
          20385,
          20482,
          20378,
          20342,
          20341,
          20337,
          20492,
          20318,
          20420,
          20334,
          20132
        ]
      },
      {
        "id": 25,
        "name": "ครูฟิม",
        "subjects": [
          "ติวเตอร์"
        ],
        "students": [
          20494,
          20493,
          20342,
          20341,
          20512
        ]
      },
      {
        "id": 2,
        "name": "ครูบิว",
        "subjects": [
          "ตีกลอง",
          "กีต้าร์"
        ],
        "students": [
          20196,
          20193,
          20189,
          20430,
          20271,
          20222,
          20192,
          20506,
          20423,
          20426,
          20178,
          20247,
          20213,
          20455,
          20413,
          20237,
          20199,
          20475,
          20187,
          20266,
          20101,
          20396,
          20186,
          20329,
          20194
        ]
      },
      {
        "id": 7,
        "name": "ครูเฟิร์น",
        "subjects": [
          "ว่ายน้ำ"
        ],
        "students": [
          20284,
          20429,
          20306,
          20419,
          20444,
          20293,
          20289,
          20104,
          20469,
          20115,
          20393,
          20075,
          20371,
          20392,
          20299,
          20291,
          20428,
          20111,
          20250,
          20480
        ]
      },
      {
        "id": 29,
        "name": "ครูโน็ต",
        "subjects": [
          "ตีกลอง",
          "เครื่องสาย",
          "ร้องเพลง (ห้องอัด)",
          "เปียโน",
          "กีต้าร์"
        ],
        "students": [
          20192,
          20484,
          20088,
          20153,
          20183,
          20140,
          20401,
          20396,
          20506,
          20217,
          20218,
          20219,
          20365,
          20261,
          20169,
          20130,
          20186,
          20212,
          20395,
          20101,
          20098,
          20204,
          20157,
          20201,
          20191
        ]
      },
      {
        "id": 6,
        "name": "ครูแอน",
        "subjects": [
          "ว่ายน้ำ"
        ],
        "students": [
          20369
        ]
      },
      {
        "id": 24,
        "name": "ครูแอปเปิ้ล",
        "subjects": [
          "เต้น"
        ],
        "students": [
          20498,
          20502,
          20503,
          20505,
          20504,
          20500,
          20499,
          20501
        ]
      },
      {
        "id": 26,
        "name": "ครูนิ้ม",
        "subjects": [
          "ตีกลอง",
          "กีต้าร์"
        ],
        "students": [
          20423,
          20157,
          20147,
          20111,
          20199,
          20210,
          20153,
          20396,
          20196,
          20403,
          20139
        ]
      }
    ],
    "subjects": [
      {
        "subject": "ร้องเพลง (ห้องอัด)",
        "studentCount": 6,
        "teacherCount": 2
      },
      {
        "subject": "ว่ายน้ำ",
        "studentCount": 65,
        "teacherCount": 6
      },
      {
        "subject": "เปียโน",
        "studentCount": 56,
        "teacherCount": 2
      },
      {
        "subject": "ติวเตอร์",
        "studentCount": 5,
        "teacherCount": 1
      },
      {
        "subject": "ตีกลอง",
        "studentCount": 35,
        "teacherCount": 3
      },
      {
        "subject": "กีต้าร์",
        "studentCount": 10,
        "teacherCount": 3
      },
      {
        "subject": "เต้น",
        "studentCount": 8,
        "teacherCount": 1
      },
      {
        "subject": "เครื่องสาย",
        "studentCount": 5,
        "teacherCount": 1
      }
    ]
  }
}